asa_core/__init__.py
asa_core/alerts.py
asa_core-0.1.0.dist-info/WHEEL
asa_core-0.1.0.dist-info/METADATA
asa_core-0.1.0.dist-info/RECORD
