Metadata-Version: 2.1
Name: asa-core
Version: 0.1.0
Summary: 
License: MIT-0
Author: Derek Sudduth
Author-email: derek.sudduth@gmail.com
Requires-Python: >=3.9,<4.0
Classifier: License :: Other/Proprietary License
Classifier: Programming Language :: Python :: 3
Classifier: Programming Language :: Python :: 3.9
Requires-Dist: boto3 (>=1.16.3,<2.0.0)
Requires-Dist: pydantic (>=1.6.1,<2.0.0)
